CHANGES.txt
CONTRIBUTORS.txt
MANIFEST.in
README.txt
setup.cfg
setup.py
Products/__init__.py
Products.mediaPerson.egg-info/PKG-INFO
Products.mediaPerson.egg-info/SOURCES.txt
Products.mediaPerson.egg-info/dependency_links.txt
Products.mediaPerson.egg-info/entry_points.txt
Products.mediaPerson.egg-info/namespace_packages.txt
Products.mediaPerson.egg-info/not-zip-safe
Products.mediaPerson.egg-info/paster_plugins.txt
Products.mediaPerson.egg-info/requires.txt
Products.mediaPerson.egg-info/top_level.txt
Products/mediaPerson/README.txt
Products/mediaPerson/__init__.py
Products/mediaPerson/config.py
Products/mediaPerson/configure.zcml
Products/mediaPerson/browser/__init__.py
Products/mediaPerson/browser/configure.zcml
Products/mediaPerson/content/__init__.py
Products/mediaPerson/content/configure.zcml
Products/mediaPerson/content/mediaperson.py
Products/mediaPerson/interfaces/__init__.py
Products/mediaPerson/interfaces/mediaperson.py
Products/mediaPerson/portlets/__init__.py
Products/mediaPerson/portlets/configure.zcml
Products/mediaPerson/profiles/default/factorytool.xml
Products/mediaPerson/profiles/default/metadata.xml
Products/mediaPerson/profiles/default/portlets.xml
Products/mediaPerson/profiles/default/rolemap.xml
Products/mediaPerson/profiles/default/types.xml
Products/mediaPerson/profiles/default/types/Media_Person.xml
Products/mediaPerson/tests/__init__.py
Products/mediaPerson/tests/base.py
Products/mediaPerson/tests/test_doctest.py
docs/HISTORY.txt
docs/INSTALL.txt
docs/LICENSE.GPL
docs/LICENSE.txt