Metadata-Version: 1.0
Name: Products.mediaPerson
Version: 0.1
Summary: Person type with folderish behaviour to store related media.
Home-page: http://svn.plone.org/svn/collective/
Author: David Jonas
Author-email: david@intk.com
License: GPL
Keywords: type folderish person
Platform: UNKNOWN
Classifier: Framework :: Plone
Classifier: Intended Audience :: Developers
Classifier: License :: OSI Approved :: GNU General Public License (GPL)
